leosheet/__init__.py
leosheet/_kernel.py
leosheet/_utils.py
leosheet-0.2.0.dist-info/LICENSE
leosheet-0.2.0.dist-info/METADATA
leosheet-0.2.0.dist-info/WHEEL
leosheet-0.2.0.dist-info/top_level.txt
leosheet-0.2.0.dist-info/RECORD
