Metadata-Version: 2.1
Name: leosheet
Version: 0.2.0
Summary: Python SDK for Google Sheet Interaction
Home-page: https://github.com/leoxiang66/leosheet
Author: Tao Xiang
Author-email: xiang.tao@outlook.de
License: UNKNOWN
Platform: UNKNOWN
Classifier: Programming Language :: Python :: 3
Classifier: License :: OSI Approved :: MIT License
License-File: LICENSE
Requires-Dist: shillelagh==1.1.5
Requires-Dist: shillelagh[gsheetsapi]
Requires-Dist: toml
